Workbook

Sheet Instrucciones
B2: Planilla de cotizaciones — XANTRAX S.R.L.
B3: Base operativa en el Parque Industrial Capital, Neuquén. Respaldo de los montos del Paso 3 de la DDJJ (Fase I: $516 M).
B5: Para qué sirve | C5: Pedir precios a proveedores, comparar hasta 3 ofertas por ítem y ver si la mejor oferta entra en el monto declarado en la DDJJ.
B6: Paso 1 | C6: Completar los datos de contacto y la fecha límite en la hoja «Pedido» (celdas amarillas).
B7: Paso 2 | C7: Filtrar la hoja «Pedido» por «Tipo de proveedor» y enviar a cada proveedor solo sus ítems. No incluye los montos de referencia.
B8: Paso 3 | C8: Cargar cada respuesta en «Comparativo»: datos del proveedor en el bloque superior y precio unitario por ítem (celdas amarillas).
B9: Paso 4 | C9: Revisar «Resumen vs DDJJ»: muestra por línea de presupuesto la mejor oferta, el desvío contra la DDJJ y los ítems sin cotizar.
B10: Celdas a completar | C10: Fondo amarillo. Texto azul = dato cargado a mano (cantidades, referencias). Texto negro = fórmula: no editar.
B11: Comparación sin IVA | C11: Las ofertas se comparan sin IVA. Si un proveedor cotiza con IVA, indicar «Sí» y la alícuota en su bloque: la planilla la descuenta.
B12: Montos de referencia | C12: Salen de la carpeta DDJJ (Paso 3, decisión de declarar $516 M). La DDJJ se declara sin IVA, igual que esta comparación.
B13: Cantidades | C13: Salen del plano de implantación (anteproyecto 1:250). El playón (970 m²) y el cerco (172 ml) se recalculan si cambian los retiros.
B14: Plazo | C14: La DDJJ se presenta el 2/11/2026: las cotizaciones tienen que llegar antes para reemplazar las estimaciones.
B16: Ejemplo de carga en «Comparativo» (formato esperado)
B17: Campo | C17: Ejemplo
B18: Proveedor | C18: Metalúrgica Ejemplo S.A.
B19: CUIT | C19: 30-00000000-0
B20: Contacto | C20: Juan Pérez — 299 400-0000 — compras@ejemplo.com
B21: Fecha de cotización | C21: 30/10/2026
B22: Validez (días) | C22: 15
B23: Precios incluyen IVA | C23: No
B24: Alícuota IVA | C24: 21%
B25: Plazo de ejecución | C25: 120 días desde el anticipo
B26: Forma de pago | C26: 40 % anticipo, saldo por certificado de avance
B27: Precio unitario ítem O-02 (m²) | C27: $ 95.000 (sin IVA) → Total = 95.000 × 350 m² = $ 33.250.000
B28: Los valores del ejemplo son ficticios: solo muestran el formato.

Sheet Pedido
A1: SOLICITUD DE COTIZACIÓN — XANTRAX S.R.L. (CUIT 30-71457180-6)
A2: Obra: base operativa, taller y depósito de herramientas de pozo — Parque Industrial Capital, Neuquén
A4: Lote / manzana | C4: Lote [N° de lote], manzana [N° de manzana]
A5: Contacto para consultas | C5: Ignacio Ramallo, socio gerente · +54 9 299 467-5788 · iramallo@xantrax.com.ar
A6: Fecha límite de respuesta | C6: [fecha límite de respuesta]
A8: Condiciones de la cotización
A9: • | B9: Precios en pesos argentinos (ARS), discriminando el IVA y su alícuota.
A10: • | B10: Validez mínima de la oferta: 15 días.
A11: • | B11: Indicar plazo de entrega o de ejecución, forma de pago y qué incluye (transporte, montaje, garantía).
A12: • | B12: Cotizar por ítem, con precio unitario y total. Se pueden proponer alternativas técnicas aclarándolas.
A13: • | B13: Las cantidades son de anteproyecto; el proyecto ejecutivo puede ajustarlas.
A15: Código | B15: Tipo de proveedor | C15: Descripción y especificación | D15: Unidad | E15: Cantidad | F15: Fase
A16: O-01 | B16: Constructora / naves metálicas | C16: Nave metálica 14 × 25 m (350 m²): fundaciones según estudio de suelos, pórticos metálicos, cerramientos laterales y cubierta de chapa prepintada, altura libre mínima 7 m, estructura dimensionada para monorriel de 3 a 5 t (a instalar en Fase II), canaletas y bajadas pluviales. | D16: gl | E16: 1 | F16: Fase I
A17: O-02 | B17: Constructora / naves metálicas | C17: Piso de hormigón armado H30 para tránsito pesado, con juntas aserradas y terminación llaneada. | D17: m² | E17: 350 | F17: Fase I
A18: O-03 | B18: Constructora / naves metálicas | C18: Portón industrial 8 × 6 m (seccional o corredizo) y puerta peatonal 1 × 2,1 m. | D18: gl | E18: 1 | F18: Fase I
A19: O-04 | B19: Instalador electricista matriculado | C19: Instalación eléctrica interior de la nave: tablero seccional, tomas industriales trifásicos y monofásicos, iluminación LED de nave. | D19: gl | E19: 1 | F19: Fase I
A20: O-05 | B20: Módulos industriales | C20: Módulo administrativo 10 × 6 m (60 m²) de alta aislación térmica: 2 oficinas y sala de reuniones, aberturas con DVH, instalación eléctrica y climatización. Incluye transporte, montaje y fundación. | D20: u | E20: 1 | F20: Fase I
A21: O-06 | B21: Módulos industriales | C21: Módulo de servicios 5 × 8 m (40 m²): vestuarios con duchas, sanitarios y comedor del personal, instalación sanitaria y termotanque. Incluye transporte, montaje y fundación. | D21: u | E21: 1 | F21: Fase I
A22: O-07 | B22: Constructora / naves metálicas | C22: Alero metálico semicubierto 10 × 5 m, altura libre 5,5 m, cubierta de chapa, adosado al frente de la nave. | D22: m² | E22: 50 | F22: Fase I
A23: O-08 | B23: Constructora / naves metálicas | C23: Platea de hormigón impermeable 10 × 5 m con pendiente y rejilla perimetral hacia la cámara separadora de hidrocarburos. | D23: m² | E23: 50 | F23: Fase I
A24: O-09 | B24: Movimiento de suelos | C24: Playón de maniobras: limpieza, compactación y enripiado técnico (espesor según estudio de suelos). | D24: m² | E24: 970 | F24: Fase I
A25: O-10 | B25: Cercos | C25: Cerco perimetral olímpico de 2 m de altura, con postes y alambre tejido. | D25: ml | E25: 172 | F25: Fase I
A26: O-11 | B26: Cercos | C26: Portón vehicular de 8 m (corredizo o de dos hojas) y puerta peatonal de 1,5 m. | D26: gl | E26: 1 | F26: Fase I
A27: O-12 | B27: Instalador electricista matriculado | C27: Conexión eléctrica trifásica, pilar de medición y tablero general (potencia a definir con la distribuidora). | D27: gl | E27: 1 | F27: Fase I
... A40: F2-03 | B40: Concesionario | C40: Camioneta 4x4 doble cabina. Cotización indicativa para la Fase II. | D40: u | E40: 1 | F40: Fase II
A42: Ítems F2-xx: cotización indicativa para la Fase II, no forman parte de la inversión de la Fase I.

Sheet Comparativo
A1: Comparativo de ofertas (montos sin IVA)
A2: Completar el bloque de cada proveedor y su precio unitario por ítem (celdas amarillas). Mejor oferta = menor total sin IVA entre los proveedores que cotizaron.
G4: Proveedor 1 | I4: Proveedor 2 | K4: Proveedor 3
F5: Proveedor
F6: CUIT
F7: Contacto
F8: Fecha de cotización
F9: Validez (días)
F10: Precios incluyen IVA (Sí/No) | G10: No | I10: No | K10: No
F11: Alícuota IVA | G11: 0.21 | I11: 0.21 | K11: 0.21
F12: Plazo de entrega / ejecución
F13: Forma de pago
A15: Código | B15: Línea | C15: Fase | D15: Descripción | E15: Unidad | F15: Cantidad | G15: P1 precio unitario | H15: P1 total sin IVA | I15: P2 precio unitario | J15: P2 total sin IVA | K15: P3 precio unitario | L15: P3 total sin IVA | M15: Mejor oferta sin IVA | N15: Proveedor de la mejor oferta | O15: Observaciones
A16: O-01 | B16: L01 | C16: Fase I | D16: Nave metálica 14 × 25 m (350 m²): fundaciones según estudio de suelos, pórticos metálicos, cerramientos laterales y cubierta de chapa prepintada, altura libre mínima 7 m, estructura dimensionada para monorriel de 3 a 5 t (a instalar en Fase II), canaletas y bajadas pluviales. | E16: gl | F16: 1 | H16: =IF(G16="","",G16*$F16/IF(G$10="Sí",1+G$11,1)) | J16: =IF(I16="","",I16*$F16/IF(I$10="Sí",1+I$11,1)) | L16: =IF(K16="","",K16*$F16/IF(K$10="Sí",1+K$11,1)) | M16: =IF(COUNT(H16,J16,L16)=0,"",MIN(H16,J16,L16)) | N16: =IF(M16="","",IF(M16=H16,$G$5,IF(M16=J16,$I$5,$K$5)))
A17: O-02 | B17: L01 | C17: Fase I | D17: Piso de hormigón armado H30 para tránsito pesado, con juntas aserradas y terminación llaneada. | E17: m² | F17: 350 | H17: =IF(G17="","",G17*$F17/IF(G$10="Sí",1+G$11,1)) | J17: =IF(I17="","",I17*$F17/IF(I$10="Sí",1+I$11,1)) | L17: =IF(K17="","",K17*$F17/IF(K$10="Sí",1+K$11,1)) | M17: =IF(COUNT(H17,J17,L17)=0,"",MIN(H17,J17,L17)) | N17: =IF(M17="","",IF(M17=H17,$G$5,IF(M17=J17,$I$5,$K$5)))
A18: O-03 | B18: L01 | C18: Fase I | D18: Portón industrial 8 × 6 m (seccional o corredizo) y puerta peatonal 1 × 2,1 m. | E18: gl | F18: 1 | H18: =IF(G18="","",G18*$F18/IF(G$10="Sí",1+G$11,1)) | J18: =IF(I18="","",I18*$F18/IF(I$10="Sí",1+I$11,1)) | L18: =IF(K18="","",K18*$F18/IF(K$10="Sí",1+K$11,1)) | M18: =IF(COUNT(H18,J18,L18)=0,"",MIN(H18,J18,L18)) | N18: =IF(M18="","",IF(M18=H18,$G$5,IF(M18=J18,$I$5,$K$5)))
A19: O-04 | B19: L01 | C19: Fase I | D19: Instalación eléctrica interior de la nave: tablero seccional, tomas industriales trifásicos y monofásicos, iluminación LED de nave. | E19: gl | F19: 1 | H19: =IF(G19="","",G19*$F19/IF(G$10="Sí",1+G$11,1)) | J19: =IF(I19="","",I19*$F19/IF(I$10="Sí",1+I$11,1)) | L19: =IF(K19="","",K19*$F19/IF(K$10="Sí",1+K$11,1)) | M19: =IF(COUNT(H19,J19,L19)=0,"",MIN(H19,J19,L19)) | N19: =IF(M19="","",IF(M19=H19,$G$5,IF(M19=J19,$I$5,$K$5)))
A20: O-05 | B20: L02 | C20: Fase I | D20: Módulo administrativo 10 × 6 m (60 m²) de alta aislación térmica: 2 oficinas y sala de reuniones, aberturas con DVH, instalación eléctrica y climatización. Incluye transporte, montaje y fundación. | E20: u | F20: 1 | H20: =IF(G20="","",G20*$F20/IF(G$10="Sí",1+G$11,1)) | J20: =IF(I20="","",I20*$F20/IF(I$10="Sí",1+I$11,1)) | L20: =IF(K20="","",K20*$F20/IF(K$10="Sí",1+K$11,1)) | M20: =IF(COUNT(H20,J20,L20)=0,"",MIN(H20,J20,L20)) | N20: =IF(M20="","",IF(M20=H20,$G$5,IF(M20=J20,$I$5,$K$5)))
A21: O-06 | B21: L03 | C21: Fase I | D21: Módulo de servicios 5 × 8 m (40 m²): vestuarios con duchas, sanitarios y comedor del personal, instalación sanitaria y termotanque. Incluye transporte, montaje y fundación. | E21: u | F21: 1 | H21: =IF(G21="","",G21*$F21/IF(G$10="Sí",1+G$11,1)) | J21: =IF(I21="","",I21*$F21/IF(I$10="Sí",1+I$11,1)) | L21: =IF(K21="","",K21*$F21/IF(K$10="Sí",1+K$11,1)) | M21: =IF(COUNT(H21,J21,L21)=0,"",MIN(H21,J21,L21)) | N21: =IF(M21="","",IF(M21=H21,$G$5,IF(M21=J21,$I$5,$K$5)))
A22: O-07 | B22: L04 | C22: Fase I | D22: Alero metálico semicubierto 10 × 5 m, altura libre 5,5 m, cubierta de chapa, adosado al frente de la nave. | E22: m² | F22: 50 | H22: =IF(G22="","",G22*$F22/IF(G$10="Sí",1+G$11,1)) | J22: =IF(I22="","",I22*$F22/IF(I$10="Sí",1+I$11,1)) | L22: =IF(K22="","",K22*$F22/IF(K$10="Sí",1+K$11,1)) | M22: =IF(COUNT(H22,J22,L22)=0,"",MIN(H22,J22,L22)) | N22: =IF(M22="","",IF(M22=H22,$G$5,IF(M22=J22,$I$5,$K$5)))
A23: O-08 | B23: L04 | C23: Fase I | D23: Platea de hormigón impermeable 10 × 5 m con pendiente y rejilla perimetral hacia la cámara separadora de hidrocarburos. | E23: m² | F23: 50 | H23: =IF(G23="","",G23*$F23/IF(G$10="Sí",1+G$11,1)) | J23: =IF(I23="","",I23*$F23/IF(I$10="Sí",1+I$11,1)) | L23: =IF(K23="","",K23*$F23/IF(K$10="Sí",1+K$11,1)) | M23: =IF(COUNT(H23,J23,L23)=0,"",MIN(H23,J23,L23)) | N23: =IF(M23="","",IF(M23=H23,$G$5,IF(M23=J23,$I$5,$K$5)))
A24: O-09 | B24: L05 | C24: Fase I | D24: Playón de maniobras: limpieza, compactación y enripiado técnico (espesor según estudio de suelos). | E24: m² | F24: 970 | H24: =IF(G24="","",G24*$F24/IF(G$10="Sí",1+G$11,1)) | J24: =IF(I24="","",I24*$F24/IF(I$10="Sí",1+I$11,1)) | L24: =IF(K24="","",K24*$F24/IF(K$10="Sí",1+K$11,1)) | M24: =IF(COUNT(H24,J24,L24)=0,"",MIN(H24,J24,L24)) | N24: =IF(M24="","",IF(M24=H24,$G$5,IF(M24=J24,$I$5,$K$5)))
A25: O-10 | B25: L05 | C25: Fase I | D25: Cerco perimetral olímpico de 2 m de altura, con postes y alambre tejido. | E25: ml | F25: 172 | H25: =IF(G25="","",G25*$F25/IF(G$10="Sí",1+G$11,1)) | J25: =IF(I25="","",I25*$F25/IF(I$10="Sí",1+I$11,1)) | L25: =IF(K25="","",K25*$F25/IF(K$10="Sí",1+K$11,1)) | M25: =IF(COUNT(H25,J25,L25)=0,"",MIN(H25,J25,L25)) | N25: =IF(M25="","",IF(M25=H25,$G$5,IF(M25=J25,$I$5,$K$5)))
A26: O-11 | B26: L05 | C26: Fase I | D26: Portón vehicular de 8 m (corredizo o de dos hojas) y puerta peatonal de 1,5 m. | E26: gl | F26: 1 | H26: =IF(G26="","",G26*$F26/IF(G$10="Sí",1+G$11,1)) | J26: =IF(I26="","",I26*$F26/IF(I$10="Sí",1+I$11,1)) | L26: =IF(K26="","",K26*$F26/IF(K$10="Sí",1+K$11,1)) | M26: =IF(COUNT(H26,J26,L26)=0,"",MIN(H26,J26,L26)) | N26: =IF(M26="","",IF(M26=H26,$G$5,IF(M26=J26,$I$5,$K$5)))
A27: O-12 | B27: L06 | C27: Fase I | D27: Conexión eléctrica trifásica, pilar de medición y tablero general (potencia a definir con la distribuidora). | E27: gl | F27: 1 | H27: =IF(G27="","",G27*$F27/IF(G$10="Sí",1+G$11,1)) | J27: =IF(I27="","",I27*$F27/IF(I$10="Sí",1+I$11,1)) | L27: =IF(K27="","",K27*$F27/IF(K$10="Sí",1+K$11,1)) | M27: =IF(COUNT(H27,J27,L27)=0,"",MIN(H27,J27,L27)) | N27: =IF(M27="","",IF(M27=H27,$G$5,IF(M27=J27,$I$5,$K$5)))
... A32: O-17 | B32: L07 | C32: Fase I | D32: Proyecto ejecutivo, plano de implantación en CAD, cálculo estructural y dirección de obra. | E32: gl | F32: 1 | H32: =IF(G32="","",G32*$F32/IF(G$10="Sí",1+G$11,1)) | J32: =IF(I32="","",I32*$F32/IF(I$10="Sí",1+I$11,1)) | L32: =IF(K32="","",K32*$F32/IF(K$10="Sí",1+K$11,1)) | M32: =IF(COUNT(H32,J32,L32)=0,"",MIN(H32,J32,L32)) | N32: =IF(M32="","",IF(M32=H32,$G$5,IF(M32=J32,$I$5,$K$5)))
A33: O-18 | B33: L07 | C33: Fase I | D33: Tasas, derechos de construcción y permisos. Estimación interna: no se pide a proveedores. | E33: gl | F33: 1 | H33: =IF(G33="","",G33*$F33/IF(G$10="Sí",1+G$11,1)) | J33: =IF(I33="","",I33*$F33/IF(I$10="Sí",1+I$11,1)) | L33: =IF(K33="","",K33*$F33/IF(K$10="Sí",1+K$11,1)) | M33: =IF(COUNT(H33,J33,L33)=0,"",MIN(H33,J33,L33)) | N33: =IF(M33="","",IF(M33=H33,$G$5,IF(M33=J33,$I$5,$K$5))) | O33: Estimación interna: cargarla como P1 con el valor estimado.
A34: E-01 | B34: L08 | C34: Fase I | D34: Banco de prueba hidrostática para herramientas de pozo, con bomba de alta presión, registrador y recinto o pantalla de protección (presión de trabajo a definir según catálogo de herramientas). | E34: u | F34: 1 | H34: =IF(G34="","",G34*$F34/IF(G$10="Sí",1+G$11,1)) | J34: =IF(I34="","",I34*$F34/IF(I$10="Sí",1+I$11,1)) | L34: =IF(K34="","",K34*$F34/IF(K$10="Sí",1+K$11,1)) | M34: =IF(COUNT(H34,J34,L34)=0,"",MIN(H34,J34,L34)) | N34: =IF(M34="","",IF(M34=H34,$G$5,IF(M34=J34,$I$5,$K$5)))
A35: E-02 | B35: L08 | C35: Fase I | D35: Hidrolavadora industrial de agua caliente. | E35: u | F35: 1 | H35: =IF(G35="","",G35*$F35/IF(G$10="Sí",1+G$11,1)) | J35: =IF(I35="","",I35*$F35/IF(I$10="Sí",1+I$11,1)) | L35: =IF(K35="","",K35*$F35/IF(K$10="Sí",1+K$11,1)) | M35: =IF(COUNT(H35,J35,L35)=0,"",MIN(H35,J35,L35)) | N35: =IF(M35="","",IF(M35=H35,$G$5,IF(M35=J35,$I$5,$K$5)))
A36: E-03 | B36: L09 | C36: Fase I | D36: Racks pesados para tubulares y herramientas largas (niveles y capacidad por nivel a definir). | E36: gl | F36: 1 | H36: =IF(G36="","",G36*$F36/IF(G$10="Sí",1+G$11,1)) | J36: =IF(I36="","",I36*$F36/IF(I$10="Sí",1+I$11,1)) | L36: =IF(K36="","",K36*$F36/IF(K$10="Sí",1+K$11,1)) | M36: =IF(COUNT(H36,J36,L36)=0,"",MIN(H36,J36,L36)) | N36: =IF(M36="","",IF(M36=H36,$G$5,IF(M36=J36,$I$5,$K$5)))
A37: E-04 | B37: L10 | C37: Fase I | D37: Herramientas de taller y metrología: calibres, micrómetros, roscas patrón y torquímetros, con certificados de calibración trazables. | E37: gl | F37: 1 | H37: =IF(G37="","",G37*$F37/IF(G$10="Sí",1+G$11,1)) | J37: =IF(I37="","",I37*$F37/IF(I$10="Sí",1+I$11,1)) | L37: =IF(K37="","",K37*$F37/IF(K$10="Sí",1+K$11,1)) | M37: =IF(COUNT(H37,J37,L37)=0,"",MIN(H37,J37,L37)) | N37: =IF(M37="","",IF(M37=H37,$G$5,IF(M37=J37,$I$5,$K$5)))
A38: E-05 | B38: L11 | C38: Fase I | D38: Equipos informáticos, red y sistema de trazabilidad de herramientas por códigos QR (etapa inicial). | E38: gl | F38: 1 | H38: =IF(G38="","",G38*$F38/IF(G$10="Sí",1+G$11,1)) | J38: =IF(I38="","",I38*$F38/IF(I$10="Sí",1+I$11,1)) | L38: =IF(K38="","",K38*$F38/IF(K$10="Sí",1+K$11,1)) | M38: =IF(COUNT(H38,J38,L38)=0,"",MIN(H38,J38,L38)) | N38: =IF(M38="","",IF(M38=H38,$G$5,IF(M38=J38,$I$5,$K$5)))
A39: F2-01 | B39: L12 | C39: Fase II | D39: Autoelevador diésel de 2,5 a 3 t. Cotización indicativa para la Fase II. | E39: u | F39: 1 | H39: =IF(G39="","",G39*$F39/IF(G$10="Sí",1+G$11,1)) | J39: =IF(I39="","",I39*$F39/IF(I$10="Sí",1+I$11,1)) | L39: =IF(K39="","",K39*$F39/IF(K$10="Sí",1+K$11,1)) | M39: =IF(COUNT(H39,J39,L39)=0,"",MIN(H39,J39,L39)) | N39: =IF(M39="","",IF(M39=H39,$G$5,IF(M39=J39,$I$5,$K$5)))
A40: F2-02 | B40: L13 | C40: Fase II | D40: Monorriel o puente grúa de 3 a 5 t con aparejo eléctrico, sobre la estructura de la nave. Cotización indicativa para la Fase II. | E40: u | F40: 1 | H40: =IF(G40="","",G40*$F40/IF(G$10="Sí",1+G$11,1)) | J40: =IF(I40="","",I40*$F40/IF(I$10="Sí",1+I$11,1)) | L40: =IF(K40="","",K40*$F40/IF(K$10="Sí",1+K$11,1)) | M40: =IF(COUNT(H40,J40,L40)=0,"",MIN(H40,J40,L40)) | N40: =IF(M40="","",IF(M40=H40,$G$5,IF(M40=J40,$I$5,$K$5)))
A41: F2-03 | B41: L14 | C41: Fase II | D41: Camioneta 4x4 doble cabina. Cotización indicativa para la Fase II. | E41: u | F41: 1 | H41: =IF(G41="","",G41*$F41/IF(G$10="Sí",1+G$11,1)) | J41: =IF(I41="","",I41*$F41/IF(I$10="Sí",1+I$11,1)) | L41: =IF(K41="","",K41*$F41/IF(K$10="Sí",1+K$11,1)) | M41: =IF(COUNT(H41,J41,L41)=0,"",MIN(H41,J41,L41)) | N41: =IF(M41="","",IF(M41=H41,$G$5,IF(M41=J41,$I$5,$K$5)))
D43: Subtotal Fase I | H43: =SUMIFS(H16:H41,$C16:$C41,"Fase I") -> 0 | J43: =SUMIFS(J16:J41,$C16:$C41,"Fase I") -> 0 | L43: =SUMIFS(L16:L41,$C16:$C41,"Fase I") -> 0 | M43: =SUMIFS(M16:M41,$C16:$C41,"Fase I") -> 0
D44: Subtotal Fase II (indicativo) | H44: =SUMIFS(H16:H41,$C16:$C41,"Fase II") -> 0 | J44: =SUMIFS(J16:J41,$C16:$C41,"Fase II") -> 0 | L44: =SUMIFS(L16:L41,$C16:$C41,"Fase II") -> 0 | M44: =SUMIFS(M16:M41,$C16:$C41,"Fase II") -> 0
D45: Los subtotales por proveedor solo suman los ítems que cada uno cotizó.

Sheet Resumen vs DDJJ
A1: Resumen: mejor oferta contra el monto declarado en la DDJJ
A2: Referencia: carpeta DDJJ, Paso 3 (Fase I declarada: $516 M sin IVA; Fase II indicativa: $130 M sin IVA). Mejor oferta sin IVA, tomada de «Comparativo».
A4: Línea | B4: Concepto | C4: Fase | D4: Grupo | E4: Referencia DDJJ | F4: Mejor oferta (suma de ítems) | G4: Diferencia | H4: Desvío | I4: Ítems | J4: Cotizados | K4: Estado
A5: L01 | B5: Nave taller y depósito 350 m² | C5: Fase I | D5: Obra | E5: 245000000 | F5: =SUMIFS(Comparativo!$M$16:$M$41,Comparativo!$B$16:$B$41,A5) -> 0 | G5: =IF(J5=0,"",F5-E5) | H5: =IF(OR(J5=0,E5=0),"",F5/E5-1) | I5: =COUNTIF(Comparativo!$B$16:$B$41,A5) -> 4 | J5: =SUMPRODUCT((Comparativo!$B$16:$B$41=A5)*ISNUMBER(Comparativo!$M$16:$M$41)) -> 0 | K5: =IF(J5=0,"Sin cotizar",IF(J5<I5,"Incompleto",IF(F5>E5,"Supera la DDJJ","Dentro de la DDJJ"))) -> Sin cotizar
A6: L02 | B6: Módulo administrativo 60 m² | C6: Fase I | D6: Obra | E6: 42000000 | F6: =SUMIFS(Comparativo!$M$16:$M$41,Comparativo!$B$16:$B$41,A6) -> 0 | G6: =IF(J6=0,"",F6-E6) | H6: =IF(OR(J6=0,E6=0),"",F6/E6-1) | I6: =COUNTIF(Comparativo!$B$16:$B$41,A6) -> 1 | J6: =SUMPRODUCT((Comparativo!$B$16:$B$41=A6)*ISNUMBER(Comparativo!$M$16:$M$41)) -> 0 | K6: =IF(J6=0,"Sin cotizar",IF(J6<I6,"Incompleto",IF(F6>E6,"Supera la DDJJ","Dentro de la DDJJ"))) -> Sin cotizar
A7: L03 | B7: Módulo de servicios, vestuarios y comedor 40 m² | C7: Fase I | D7: Obra | E7: 28000000 | F7: =SUMIFS(Comparativo!$M$16:$M$41,Comparativo!$B$16:$B$41,A7) -> 0 | G7: =IF(J7=0,"",F7-E7) | H7: =IF(OR(J7=0,E7=0),"",F7/E7-1) | I7: =COUNTIF(Comparativo!$B$16:$B$41,A7) -> 1 | J7: =SUMPRODUCT((Comparativo!$B$16:$B$41=A7)*ISNUMBER(Comparativo!$M$16:$M$41)) -> 0 | K7: =IF(J7=0,"Sin cotizar",IF(J7<I7,"Incompleto",IF(F7>E7,"Supera la DDJJ","Dentro de la DDJJ"))) -> Sin cotizar
A8: L04 | B8: Alero semicubierto 50 m² con platea impermeable | C8: Fase I | D8: Obra | E8: 18000000 | F8: =SUMIFS(Comparativo!$M$16:$M$41,Comparativo!$B$16:$B$41,A8) -> 0 | G8: =IF(J8=0,"",F8-E8) | H8: =IF(OR(J8=0,E8=0),"",F8/E8-1) | I8: =COUNTIF(Comparativo!$B$16:$B$41,A8) -> 2 | J8: =SUMPRODUCT((Comparativo!$B$16:$B$41=A8)*ISNUMBER(Comparativo!$M$16:$M$41)) -> 0 | K8: =IF(J8=0,"Sin cotizar",IF(J8<I8,"Incompleto",IF(F8>E8,"Supera la DDJJ","Dentro de la DDJJ"))) -> Sin cotizar
A9: L05 | B9: Playón, cerco perimetral y portón | C9: Fase I | D9: Obra | E9: 50000000 | F9: =SUMIFS(Comparativo!$M$16:$M$41,Comparativo!$B$16:$B$41,A9) -> 0 | G9: =IF(J9=0,"",F9-E9) | H9: =IF(OR(J9=0,E9=0),"",F9/E9-1) | I9: =COUNTIF(Comparativo!$B$16:$B$41,A9) -> 3 | J9: =SUMPRODUCT((Comparativo!$B$16:$B$41=A9)*ISNUMBER(Comparativo!$M$16:$M$41)) -> 0 | K9: =IF(J9=0,"Sin cotizar",IF(J9<I9,"Incompleto",IF(F9>E9,"Supera la DDJJ","Dentro de la DDJJ"))) -> Sin cotizar
A10: L06 | B10: Servicios e instalaciones | C10: Fase I | D10: Obra | E10: 38000000 | F10: =SUMIFS(Comparativo!$M$16:$M$41,Comparativo!$B$16:$B$41,A10) -> 0 | G10: =IF(J10=0,"",F10-E10) | H10: =IF(OR(J10=0,E10=0),"",F10/E10-1) | I10: =COUNTIF(Comparativo!$B$16:$B$41,A10) -> 4 | J10: =SUMPRODUCT((Comparativo!$B$16:$B$41=A10)*ISNUMBER(Comparativo!$M$16:$M$41)) -> 0 | K10: =IF(J10=0,"Sin cotizar",IF(J10<I10,"Incompleto",IF(F10>E10,"Supera la DDJJ","Dentro de la DDJJ"))) -> Sin cotizar
A11: L07 | B11: Proyecto, dirección de obra, estudio de suelos y permisos | C11: Fase I | D11: Obra | E11: 25000000 | F11: =SUMIFS(Comparativo!$M$16:$M$41,Comparativo!$B$16:$B$41,A11) -> 0 | G11: =IF(J11=0,"",F11-E11) | H11: =IF(OR(J11=0,E11=0),"",F11/E11-1) | I11: =COUNTIF(Comparativo!$B$16:$B$41,A11) -> 3 | J11: =SUMPRODUCT((Comparativo!$B$16:$B$41=A11)*ISNUMBER(Comparativo!$M$16:$M$41)) -> 0 | K11: =IF(J11=0,"Sin cotizar",IF(J11<I11,"Incompleto",IF(F11>E11,"Supera la DDJJ","Dentro de la DDJJ"))) -> Sin cotizar
A12: L08 | B12: Banco de prueba hidrostática y lavadora | C12: Fase I | D12: Equipamiento | E12: 32000000 | F12: =SUMIFS(Comparativo!$M$16:$M$41,Comparativo!$B$16:$B$41,A12) -> 0 | G12: =IF(J12=0,"",F12-E12) | H12: =IF(OR(J12=0,E12=0),"",F12/E12-1) | I12: =COUNTIF(Comparativo!$B$16:$B$41,A12) -> 2 | J12: =SUMPRODUCT((Comparativo!$B$16:$B$41=A12)*ISNUMBER(Comparativo!$M$16:$M$41)) -> 0 | K12: =IF(J12=0,"Sin cotizar",IF(J12<I12,"Incompleto",IF(F12>E12,"Supera la DDJJ","Dentro de la DDJJ"))) -> Sin cotizar
A13: L09 | B13: Racks pesados | C13: Fase I | D13: Equipamiento | E13: 18000000 | F13: =SUMIFS(Comparativo!$M$16:$M$41,Comparativo!$B$16:$B$41,A13) -> 0 | G13: =IF(J13=0,"",F13-E13) | H13: =IF(OR(J13=0,E13=0),"",F13/E13-1) | I13: =COUNTIF(Comparativo!$B$16:$B$41,A13) -> 1 | J13: =SUMPRODUCT((Comparativo!$B$16:$B$41=A13)*ISNUMBER(Comparativo!$M$16:$M$41)) -> 0 | K13: =IF(J13=0,"Sin cotizar",IF(J13<I13,"Incompleto",IF(F13>E13,"Supera la DDJJ","Dentro de la DDJJ"))) -> Sin cotizar
A14: L10 | B14: Herramientas de taller y metrología | C14: Fase I | D14: Equipamiento | E14: 13000000 | F14: =SUMIFS(Comparativo!$M$16:$M$41,Comparativo!$B$16:$B$41,A14) -> 0 | G14: =IF(J14=0,"",F14-E14) | H14: =IF(OR(J14=0,E14=0),"",F14/E14-1) | I14: =COUNTIF(Comparativo!$B$16:$B$41,A14) -> 1 | J14: =SUMPRODUCT((Comparativo!$B$16:$B$41=A14)*ISNUMBER(Comparativo!$M$16:$M$41)) -> 0 | K14: =IF(J14=0,"Sin cotizar",IF(J14<I14,"Incompleto",IF(F14>E14,"Supera la DDJJ","Dentro de la DDJJ"))) -> Sin cotizar
A15: L11 | B15: Informática y trazabilidad QR | C15: Fase I | D15: Equipamiento | E15: 7000000 | F15: =SUMIFS(Comparativo!$M$16:$M$41,Comparativo!$B$16:$B$41,A15) -> 0 | G15: =IF(J15=0,"",F15-E15) | H15: =IF(OR(J15=0,E15=0),"",F15/E15-1) | I15: =COUNTIF(Comparativo!$B$16:$B$41,A15) -> 1 | J15: =SUMPRODUCT((Comparativo!$B$16:$B$41=A15)*ISNUMBER(Comparativo!$M$16:$M$41)) -> 0 | K15: =IF(J15=0,"Sin cotizar",IF(J15<I15,"Incompleto",IF(F15>E15,"Supera la DDJJ","Dentro de la DDJJ"))) -> Sin cotizar
A16: L12 | B16: Autoelevador | C16: Fase II | D16: Equipamiento | E16: 45000000 | F16: =SUMIFS(Comparativo!$M$16:$M$41,Comparativo!$B$16:$B$41,A16) -> 0 | G16: =IF(J16=0,"",F16-E16) | H16: =IF(OR(J16=0,E16=0),"",F16/E16-1) | I16: =COUNTIF(Comparativo!$B$16:$B$41,A16) -> 1 | J16: =SUMPRODUCT((Comparativo!$B$16:$B$41=A16)*ISNUMBER(Comparativo!$M$16:$M$41)) -> 0 | K16: =IF(J16=0,"Sin cotizar",IF(J16<I16,"Incompleto",IF(F16>E16,"Supera la DDJJ","Dentro de la DDJJ"))) -> Sin cotizar
... A18: L14 | B18: Camioneta 4x4 | C18: Fase II | D18: Equipamiento | E18: 55000000 | F18: =SUMIFS(Comparativo!$M$16:$M$41,Comparativo!$B$16:$B$41,A18) -> 0 | G18: =IF(J18=0,"",F18-E18) | H18: =IF(OR(J18=0,E18=0),"",F18/E18-1) | I18: =COUNTIF(Comparativo!$B$16:$B$41,A18) -> 1 | J18: =SUMPRODUCT((Comparativo!$B$16:$B$41=A18)*ISNUMBER(Comparativo!$M$16:$M$41)) -> 0 | K18: =IF(J18=0,"Sin cotizar",IF(J18<I18,"Incompleto",IF(F18>E18,"Supera la DDJJ","Dentro de la DDJJ"))) -> Sin cotizar
B20: Obra — Fase I | E20: =SUMIFS(E5:E18,C5:C18,"Fase I",D5:D18,"Obra") -> 446000000 | F20: =SUMIFS(F5:F18,C5:C18,"Fase I",D5:D18,"Obra") -> 0 | G20: =IF(F20=0,"",F20-E20) | H20: =IF(OR(F20=0,E20=0),"",F20/E20-1) | I20: =SUMIFS(I5:I18,C5:C18,"Fase I",D5:D18,"Obra") -> 18 | J20: =SUMIFS(J5:J18,C5:C18,"Fase I",D5:D18,"Obra") -> 0 | K20: =IF(J20=0,"Sin cotizar",IF(J20<I20,"Incompleto",IF(F20>E20,"Supera la DDJJ","Dentro de la DDJJ"))) -> Sin cotizar
B21: Equipamiento — Fase I | E21: =SUMIFS(E5:E18,C5:C18,"Fase I",D5:D18,"Equipamiento") -> 70000000 | F21: =SUMIFS(F5:F18,C5:C18,"Fase I",D5:D18,"Equipamiento") -> 0 | G21: =IF(F21=0,"",F21-E21) | H21: =IF(OR(F21=0,E21=0),"",F21/E21-1) | I21: =SUMIFS(I5:I18,C5:C18,"Fase I",D5:D18,"Equipamiento") -> 5 | J21: =SUMIFS(J5:J18,C5:C18,"Fase I",D5:D18,"Equipamiento") -> 0 | K21: =IF(J21=0,"Sin cotizar",IF(J21<I21,"Incompleto",IF(F21>E21,"Supera la DDJJ","Dentro de la DDJJ"))) -> Sin cotizar
B22: TOTAL FASE I (monto declarado) | E22: =E20+E21 -> 516000000 | F22: =F20+F21 -> 0 | G22: =IF(F22=0,"",F22-E22) | H22: =IF(OR(F22=0,E22=0),"",F22/E22-1) | I22: =I20+I21 -> 23 | J22: =J20+J21 -> 0 | K22: =IF(J22=0,"Sin cotizar",IF(J22<I22,"Incompleto",IF(F22>E22,"Supera la DDJJ","Dentro de la DDJJ"))) -> Sin cotizar
B23: Fase II (indicativo) | E23: =SUMIFS(E5:E18,C5:C18,"Fase II") -> 130000000 | F23: =SUMIFS(F5:F18,C5:C18,"Fase II") -> 0 | G23: =IF(F23=0,"",F23-E23) | H23: =IF(OR(F23=0,E23=0),"",F23/E23-1) | I23: =SUMIFS(I5:I18,C5:C18,"Fase II") -> 3 | J23: =SUMIFS(J5:J18,C5:C18,"Fase II") -> 0 | K23: =IF(J23=0,"Sin cotizar",IF(J23<I23,"Incompleto",IF(F23>E23,"Supera la DDJJ","Dentro de la DDJJ"))) -> Sin cotizar
B25: La diferencia y el desvío solo se calculan cuando la línea tiene al menos un ítem cotizado; una línea «Incompleta» subestima el costo real.
B26: Línea L07 incluye tasas y permisos (O-18), que no se piden a proveedores: cargar la estimación interna en «Comparativo».
B27: La DDJJ se declara sin IVA: las referencias y las ofertas se comparan sobre la misma base.
